bluedo/__init__.py
bluedo/bluedo.png
bluedo/bluedoapp.py
bluedo/bt_rssi.py
bluedo/lock_animation.gif
bluedo/phonelink-white-18dp.svg
bluedo/phonelink_off-white-18dp.svg
bluedo/unlocked.png
bluedo/window.glade
bluedo-2.5.data/data/share/applications/bluedo.desktop
bluedo-2.5.data/data/share/icons/hicolor/256x256/apps/bluedo.png
bluedo-2.5.dist-info/LICENSE
bluedo-2.5.dist-info/METADATA
bluedo-2.5.dist-info/WHEEL
bluedo-2.5.dist-info/entry_points.txt
bluedo-2.5.dist-info/top_level.txt
bluedo-2.5.dist-info/RECORD
