Metadata-Version: 2.1
Name: bluedo
Version: 2.5
Summary: Bluetooth proximity automation
Home-page: https://github.com/ways/BlueDo/
Author: Lars Falk-Petersen
Author-email: dev@falkp.no
License: GPLv3+
Keywords: bluetooth
Platform: UNKNOWN
Classifier: Development Status :: 4 - Beta
Classifier: Intended Audience :: End Users/Desktop
Classifier: License :: OSI Approved :: GNU General Public License v3 or later (GPLv3+)
Classifier: Programming Language :: Python :: 3
Classifier: Programming Language :: Python :: 3.10
Classifier: Programming Language :: Python :: 3.11
Classifier: Topic :: Desktop Environment
Classifier: Topic :: Desktop Environment :: Gnome
Classifier: Topic :: Security
Classifier: Environment :: X11 Applications :: Gnome
Classifier: Operating System :: POSIX :: Linux
Classifier: Natural Language :: English
Requires-Python: >=3.10
License-File: LICENSE
Requires-Dist: PyGObject
Requires-Dist: appdirs
Requires-Dist: configparser
Requires-Dist: setuptools
Requires-Dist: wheel
